starferry/__init__.py
starferry/main.py
starferry/routers/__init__.py
starferry/routers/bingo.py
starferry/routers/finance.py
starferry/services/__init__.py
starferry/services/gemini_service.py
starferry/services/grok_service.py
starferry/services/openai_service.py
starferry/services/sovits_service.py
starferry/services/token_service.py
starferry/utils/__init__.py
starferry/utils/ip_tracker.py
starferry-0.1.1.dist-info/METADATA
starferry-0.1.1.dist-info/WHEEL
starferry-0.1.1.dist-info/RECORD
