Metadata-Version: 2.4
Name: starferry
Version: 0.1.1
Summary: FastAPI-based API service that generates custom bingo game items using multiple AI providers
Project-URL: Homepage, https://github.com/JerrySu5379/Starferry
Project-URL: Bug Tracker, https://github.com/JerrySu5379/Starferry/issues
Author-email: JerrySu5379 <jerrysu5379@gmail.com>
License: MIT
Classifier: License :: OSI Approved :: MIT License
Classifier: Operating System :: OS Independent
Classifier: Programming Language :: Python :: 3
Requires-Python: >=3.10
Requires-Dist: fastapi>=0.95.0
